[
    {
        "name": "Agricultural and Bioenvironmental Engineering",
        "school": "School of Engineering Technology"
    },
    {
        "name": "Chemical Engineering",
        "school": "School of Engineering Technology"
    },
    {
        "name": "Civil Engineering",
        "school": "School of Engineering Technology"
    },
    {
        "name": "Computer Engineering",
        "school": "School of Engineering Technology"
    },
    {
        "name": "Electrical/Electronics Engineering",
        "school": "School of Engineering Technology"
    },
    {
        "name": "Mechanical Engineering",
        "school": "School of Engineering Technology"
    },
    {
        "name": "Mechatronics Engineering",
        "school": "School of Engineering Technology"
    },
    {
        "name": "Mineral and Petroleum Engineering",
        "school": "School of Engineering Technology"
    },
    {
        "name": "Material and Metallurgical Engineering",
        "school": "School of Engineering Technology"
    },
    {
        "name": "Welding and Fabrication Engineering",
        "school": "School of Engineering Technology"
    },
    {
        "name": "Science Laboratory Technology",
        "school": "School of Industrial and Applied Science"
    },
    {
        "name": "Food Technology",
        "school": "School of Industrial and Applied Science"
    },
    {
        "name": "Mathematics and Statistics",
        "school": "School of Industrial and Applied Science"
    },
    {
        "name": "Fisheries Technology",
        "school": "School of Industrial and Applied Science"
    },
    {
        "name": "Hospitality Management",
        "school": "School of Industrial and Applied Science"
    },
    {
        "name": "Agricultural Technology",
        "school": "School of Industrial and Applied Science"
    },
    {
        "name": "Printing Technology",
        "school": "School of Industrial and Applied Science"
    },
    {
        "name": "Accountancy",
        "school": "School of Business and Management Technology"
    },
    {
        "name": "Business Administration and Management",
        "school": "School of Business and Management Technology"
    },
    {
        "name": "Banking and Finance",
        "school": "School of Business and Management Technology"
    },
    {
        "name": "Cooperative Economics and Management",
        "school": "School of Business and Management Technology"
    },
    {
        "name": "Marketing",
        "school": "School of Business and Management Technology"
    },
    {
        "name": "Office Technology and Management",
        "school": "School of Business and Management Technology"
    },
    {
        "name": "Public Administration",
        "school": "School of Business and Management Technology"
    },
    {
        "name": "Procurement and Supply Chain Management",
        "school": "School of Business and Management Technology"
    },
    {
        "name": "Taxation",
        "school": "School of Business and Management Technology"
    },
    {
        "name": "Mass Communication",
        "school": "School of General Studies"
    },
    {
        "name": "Agricultural Technology",
        "school": "School of Agriculture and Agricultural Technology"
    },
    {
        "name": "Animal Health and Production Technology",
        "school": "School of Agriculture and Agricultural Technology"
    },
    {
        "name": "Fisheries Technology",
        "school": "School of Agriculture and Agricultural Technology"
    },
    {
        "name": "Architecture Technology",
        "school": "School of Environmental Design and Technology"
    },
    {
        "name": "Building Technology",
        "school": "School of Environmental Design and Technology"
    },
    {
        "name": "Estate Management Technology",
        "school": "School of Environmental Design and Technology"
    },
    {
        "name": "Quantity Surveying Technology",
        "school": "School of Environmental Design and Technology"
    },
    {
        "name": "Urban and Regional Planning Technology",
        "school": "School of Environmental Design and Technology"
    },
    {
        "name": "Surveying and Geo-Informatics Technology",
        "school": "School of Environmental Design and Technology"
    },
    {
        "name": "Arts and Design Technology",
        "school": "School of Environmental Design and Technology"
    },
    {
        "name": "Computer Science",
        "school": "School of Information and Communication Technology"
    },
    {
        "name": "Library and Information Science",
        "school": "School of Information and Communication Technology"
    }
]
